kafkastreamer/__init__.py
kafkastreamer/apps.py
kafkastreamer/constants.py
kafkastreamer/context.py
kafkastreamer/decorators.py
kafkastreamer/funcs.py
kafkastreamer/handlers.py
kafkastreamer/partitioners.py
kafkastreamer/py.typed
kafkastreamer/registry.py
kafkastreamer/serializers.py
kafkastreamer/settings.py
kafkastreamer/squashing.py
kafkastreamer/stream.py
kafkastreamer/tasks.py
kafkastreamer/types.py
kafkastreamer/management/__init__.py
kafkastreamer/management/commands/__init__.py
kafkastreamer/management/commands/kafkastreamer_refresh.py
django_kafka_streamer-1.4.1.dist-info/LICENSE
django_kafka_streamer-1.4.1.dist-info/METADATA
django_kafka_streamer-1.4.1.dist-info/WHEEL
django_kafka_streamer-1.4.1.dist-info/top_level.txt
django_kafka_streamer-1.4.1.dist-info/RECORD
