Metadata-Version: 2.1
Name: django-kafka-streamer
Version: 1.4.1
Summary: Stream data to Apache Kafka.
Author-email: Kostiantyn Korikov <lostclus@gmail.com>
Project-URL: Repository, http://github.com/lostclus/django-kafka-streamer
Project-URL: Documentation, http://django-kafka-streamer.readthedocs.io/
Keywords: Django,Kafka,microservices
Classifier: Development Status :: 4 - Beta
Classifier: Environment :: Web Environment
Classifier: Intended Audience :: Developers
Classifier: License :: OSI Approved :: BSD License
Classifier: Operating System :: OS Independent
Classifier: Programming Language :: Python
Classifier: Programming Language :: Python :: 3
Classifier: Programming Language :: Python :: 3.10
Classifier: Programming Language :: Python :: 3.11
Classifier: Programming Language :: Python :: 3.12
Classifier: Programming Language :: Python :: 3.13
Classifier: Framework :: Django
Classifier: Framework :: Django :: 3
Classifier: Framework :: Django :: 3.2
Classifier: Framework :: Django :: 4
Classifier: Framework :: Django :: 4.0
Classifier: Framework :: Django :: 4.1
Classifier: Framework :: Django :: 4.2
Classifier: Framework :: Django :: 5.0
Classifier: Framework :: Django :: 5.1
Classifier: Typing :: Typed
Requires-Python: >=3.10
License-File: LICENSE
Requires-Dist: Django >=3.2
Requires-Dist: kafka-python-ng >=2.2.2
Requires-Dist: celery >=5.1.0
Provides-Extra: docs
Requires-Dist: sphinx ; extra == 'docs'
Requires-Dist: sphinx-rtd-theme ; extra == 'docs'
Provides-Extra: tests
Requires-Dist: pytest ; extra == 'tests'
Requires-Dist: pytest-cov ; extra == 'tests'
Requires-Dist: pytest-djangoapp ; extra == 'tests'
